[
    {
        "n": "gacha/feature_movie/new_character_pickup_13/pirates_gunner/.gen/feature/a",
        "w": 20,
        "h": 20,
        "x": 1,
        "y": 989
    },
    {
        "n": "gacha/feature_movie/new_character_pickup_13/pirates_gunner/.gen/feature/b",
        "w": 248,
        "h": 207,
        "x": 500,
        "y": 799,
        "r": true,
        "fx": -35,
        "fy": -14,
        "fw": 276,
        "fh": 276
    },
    {
        "n": "gacha/feature_movie/new_character_pickup_13/pirates_gunner/.gen/feature/c",
        "w": 676,
        "h": 248,
        "x": 2060,
        "y": 723,
        "fx": -151,
        "fy": -60,
        "fw": 1016,
        "fh": 360
    },
    {
        "n": "gacha/feature_movie/new_character_pickup_13/pirates_gunner/.gen/feature/d",
        "w": 248,
        "h": 675,
        "x": 2342,
        "y": 1,
        "r": true,
        "fx": -151,
        "fy": -60,
        "fw": 1016,
        "fh": 360
    },
    {
        "n": "gacha/feature_movie/new_character_pickup_13/pirates_gunner/.gen/feature/e",
        "w": 104,
        "h": 104,
        "x": 1093,
        "y": 799,
        "fx": -3,
        "fy": -3,
        "fw": 110,
        "fh": 110
    },
    {
        "n": "gacha/feature_movie/new_character_pickup_13/pirates_gunner/.gen/feature/f",
        "w": 280,
        "h": 720,
        "x": 2060,
        "y": 1,
        "r": true
    },
    {
        "n": "gacha/feature_movie/new_character_pickup_13/pirates_gunner/.gen/feature/g",
        "w": 235,
        "h": 627,
        "x": 2592,
        "y": 1,
        "r": true,
        "fx": -177,
        "fy": -66,
        "fw": 1016,
        "fh": 360
    },
    {
        "n": "gacha/feature_movie/new_character_pickup_13/pirates_gunner/.gen/feature/h",
        "w": 20,
        "h": 20,
        "x": 23,
        "y": 989
    },
    {
        "n": "gacha/feature_movie/new_character_pickup_13/pirates_gunner/.gen/feature/i",
        "w": 128,
        "h": 138,
        "x": 832,
        "y": 799,
        "fx": -5,
        "fy": 0,
        "fw": 138,
        "fh": 138
    },
    {
        "n": "gacha/feature_movie/new_character_pickup_13/pirates_gunner/.gen/feature/j",
        "w": 129,
        "h": 129,
        "x": 962,
        "y": 799,
        "fx": -1,
        "fy": -1,
        "fw": 130,
        "fh": 130
    },
    {
        "n": "gacha/feature_movie/new_character_pickup_13/pirates_gunner/.gen/feature/k",
        "w": 233,
        "h": 233,
        "x": 2738,
        "y": 630
    },
    {
        "n": "gacha/feature_movie/new_character_pickup_13/pirates_gunner/.gen/feature/l",
        "w": 497,
        "h": 188,
        "x": 1,
        "y": 799,
        "fx": -7,
        "fy": -114,
        "fw": 680,
        "fh": 380
    },
    {
        "n": "gacha/feature_movie/new_character_pickup_13/pirates_gunner/.gen/feature/m",
        "w": 254,
        "h": 53,
        "x": 832,
        "y": 939,
        "fx": -124,
        "fy": -8,
        "fw": 500,
        "fh": 64
    },
    {
        "n": "gacha/feature_movie/new_character_pickup_13/pirates_gunner/.gen/feature/n",
        "w": 80,
        "h": 220,
        "x": 750,
        "y": 799,
        "r": true,
        "fx": -247,
        "fy": -14,
        "fw": 720,
        "fh": 100
    },
    {
        "n": "gacha/feature_movie/new_character_pickup_13/pirates_gunner/.gen/feature/o",
        "w": 251,
        "h": 42,
        "x": 1088,
        "y": 930,
        "fx": -53,
        "fy": -8,
        "fw": 360,
        "fh": 54
    },
    {
        "n": "gacha/feature_movie/new_character_pickup_13/pirates_gunner/.gen/feature/p",
        "w": 1440,
        "h": 234,
        "x": 1,
        "y": 563,
        "fx": 0,
        "fy": -7,
        "fw": 1440,
        "fh": 241
    },
    {
        "n": "gacha/feature_movie/new_character_pickup_13/pirates_gunner/.gen/feature/q",
        "w": 615,
        "h": 1000,
        "x": 1443,
        "y": 1,
        "r": true,
        "fx": -66,
        "fy": 0,
        "fw": 1440,
        "fh": 615
    },
    {
        "n": "gacha/feature_movie/new_character_pickup_13/pirates_gunner/.gen/feature/r",
        "w": 1440,
        "h": 560,
        "x": 1,
        "y": 1
    },
    {
        "n": "gacha/feature_movie/new_character_pickup_13/pirates_gunner/.gen/feature/s",
        "w": 20,
        "h": 20,
        "x": 45,
        "y": 989
    }
]